postcodinator/__init__.py
postcodinator/postcodinator.py
postcodinator/data/postcode_data.parquet
postcodinator-0.1.5.dist-info/METADATA
postcodinator-0.1.5.dist-info/WHEEL
postcodinator-0.1.5.dist-info/top_level.txt
postcodinator-0.1.5.dist-info/RECORD
