Metadata-Version: 2.1
Name: postcodinator
Version: 0.1.5
Summary: A package to get info on UK post codes
Author: Stephen Bourne
Author-email: hello@stephenbourne.dev
Classifier: Programming Language :: Python :: 3
Classifier: License :: OSI Approved :: MIT License
Classifier: Operating System :: OS Independent
Requires-Python: >=3.7
Requires-Dist: pandas
Requires-Dist: pyarrow
